Workbook

Sheet README
A1: GovCon Proposal Cost Build & Program Profitability Model
A2: Built by Prakash Balasubramanian | Data: USASpending.gov + DCAA Benchmarks + Modeled Synthetic Actuals
A4: PURPOSE
A5: Item | B5: Detail | C5: Notes
A6: What this model does | B6: Replicates proposal cost buildup and program profitability analysis performed by a Project Financial Analyst in a GovCon environment. | C6: Covers direct labor, indirect stack, fee by contract type, scenario analysis, and margin tracking.
A7: Who would use this | B7: Project Financial Analyst, Program Manager, Pricing Lead | C7: Supports proposal submission, EAC updates, and monthly financial reviews.
A9: DATA SOURCES — WHAT IS REAL (Public Records)
A10: Data Element | B10: Value / Range | C10: Source
A11: Contract award numbers | B11: 75FCMC22F0046 | 70T02021F7560N005 | 75N97023F00001 | C11: USASpending.gov
A12: Awarding agencies | B12: HHS/CMS | Dept. of Homeland Security | HHS/NIH | C12: USASpending.gov
A13: Contract ceiling values | B13: $8.07M | $1.01M | $7.34M | C13: USASpending.gov cumulative obligations
A14: NAICS codes | B14: 541512 | 541611 | 541512 | C14: USASpending.gov
A15: Fringe rate range | B15: 29% to 36% | C15: DCAA provisional rate guidance NAICS 541
A16: Overhead rate range | B16: 41% to 51% | C16: DCAA provisional rate guidance NAICS 541
A17: G&A rate range | B17: 10% to 15% | C17: DCAA provisional rate guidance NAICS 541
A18: CPFF fee cap | B18: 7% per FAR 15.404-4 | C18: Federal Acquisition Regulation
A19: Labor bill rate benchmarks | B19: GSA Schedule SIN rates for IT and consulting | C19: GSA Multiple Award Schedule
A21: DATA SOURCES — WHAT IS SYNTHETIC (Modeled)
A22: Data Element | B22: Why Synthetic | C22: Analogy to Live Environment
A23: Monthly cost actuals | B23: Internal contractor records — never publicly disclosed | C23: Data pulled from Deltek Costpoint each period
A24: Labor hours by category | B24: Internal timesheet data — proprietary | C24: Timesheet system such as Deltek Time and Expense
A25: EAC projections | B25: Internal monthly EAC updates — not reported to USASpending | C25: Monthly EAC submitted to Program Manager
A26: Subcontractor cost breakdown | B26: Internal invoice data — proprietary | C26: Subcontractor invoice reconciliation in Costpoint
A27: Budget by period | B27: Internal program baseline — proprietary | C27: Contract budget loaded into Costpoint at award
A29: WORKBOOK GUIDE
A30: Tab | B30: Contents | C30: Primary User
A31: Indirect_Rates | B31: Rate inputs (Fringe, Overhead, G&A, Fee). Change here — all tabs update automatically. | C31: Financial Analyst / Pricing Lead
A32: Cost_Build | B32: Full proposal cost buildup: direct labor, indirect stack, fee by contract type, scenario analysis. | C32: Financial Analyst / Program Manager
A33: Profitability | B33: Program-level margin tracking across 3 real contracts. Revenue, cost, gross margin, fee at risk. | C33: Program Manager / Finance Director
A35: COLOR CODING LEGEND
A36: Blue text | B36: Hardcoded input — number you can change
A37: Black text | B37: Formula or calculation — do not overwrite
A38: Green text | B38: Cross-sheet link from another tab

Sheet Indirect_Rates
A1: Indirect Rate Assumptions — Adjust Rates Here to Update All Tabs
A2: Rates benchmarked to DCAA provisional rate guidance for NAICS 541 Professional Services
A4: INDIRECT RATES | Blue = hardcoded input you can change
A5: Rate Type | B5: Current Rate | C5: Low Scenario | D5: High Scenario | E5: DCAA Benchmark Range | F5: Source
A6: Fringe | B6: 0.32 | C6: 0.29 | D6: 0.36 | E6: 29% to 36% | F6: DCAA provisional rate guidance NAICS 541
A7: Overhead | B7: 0.45 | C7: 0.41 | D7: 0.51 | E7: 41% to 51% | F7: DCAA provisional rate guidance NAICS 541
A8: G&A | B8: 0.12 | C8: 0.1 | D8: 0.15 | E8: 10% to 15% | F8: DCAA provisional rate guidance NAICS 541
A10: FEE RATES BY CONTRACT TYPE | Per FAR 15.404-4 and industry practice
A11: Contract Type | B11: Current Fee | C11: Low Scenario | D11: High Scenario | E11: Regulatory Basis | F11: Source
A12: Cost-Plus-Fixed-Fee (CPFF) | B12: 0.07 | C12: 0.06 | D12: 0.08 | E12: FAR 15.404-4 statutory cap 10%, typical 6-8% | F12: Federal Acquisition Regulation
A13: Time and Materials (T&M) | B13: 0.1 | C13: 0.08 | D13: 0.12 | E13: No statutory cap; market range 8-12% | F13: Industry standard GovCon professional services
A14: Firm-Fixed-Price (FFP) | B14: 0.12 | C14: 0.1 | D14: 0.15 | E14: No statutory cap; residual profit 10-15% | F14: Industry standard GovCon professional services
A16: Note: All blue cells are inputs. Change them here and Cost_Build and Profitability update automatically.

Sheet Cost_Build
A1: GovCon Proposal Cost Buildup Model
A2: Rates pull automatically from Indirect_Rates tab — adjust rates there to update this entire model
A4: SECTION 1 — DIRECT LABOR INPUTS | Blue = inputs you can change
A5: Labor Category | B5: Hours | C5: Bill Rate ($/hr) | D5: Direct Labor Cost
A6: Program Manager | B6: 480 | C6: 182 | D6: =B6*C6
A7: Senior Systems Analyst | B7: 960 | C7: 148 | D7: =B7*C7
A8: Cybersecurity Analyst | B8: 1040 | C8: 138 | D8: =B8*C8
A9: Management Consultant | B9: 640 | C9: 145 | D9: =B9*C9
A10: IT Solutions Architect | B10: 520 | C10: 198 | D10: =B10*C10
A11: Junior Analyst | B11: 800 | C11: 92 | D11: =B11*C11
A12: TOTAL DIRECT LABOR | D12: =SUM(D6:D11)
A14: SECTION 2 — INDIRECT COST STACK | Rates link from Indirect_Rates tab
A15: Cost Element | B15: Rate | C15: Base Amount | D15: Cost Amount
A16: Direct Labor | D16: =D12
A17: Fringe | B17: =Indirect_Rates!B6 | C17: =D16 | D17: =B17*C17
A18: Overhead | B18: =Indirect_Rates!B7 | C18: =D16 | D18: =B18*C18
A19: Subtotal (DL + Fringe + OH) | D19: =D16+D17+D18
A20: G&A | B20: =Indirect_Rates!B8 | C20: =D19 | D20: =B20*C20
A21: TOTAL COST INPUT (TCI) | D21: =D19+D20
A23: SECTION 3 — FEE AND TOTAL PRICE BY CONTRACT TYPE
A24: Contract Type | B24: Fee Rate | C24: Fee Amount | D24: Total Contract Price | E24: Gross Margin %
A25: Cost-Plus-Fixed-Fee (CPFF) | B25: =Indirect_Rates!B12 | C25: =B25*D21 | D25: =D21+C25 | E25: =C25/D25
A26: Time and Materials (T&M) | B26: =Indirect_Rates!B13 | C26: =B26*D21 | D26: =D21+C26 | E26: =C26/D26
A27: Firm-Fixed-Price (FFP) | B27: =Indirect_Rates!B14 | C27: =B27*D21 | D27: =D21+C27 | E27: =C27/D27
A29: SECTION 4 — INDIRECT RATE SCENARIO ANALYSIS | Impact on total FFP contract price
A30: Scenario | B30: Fringe | C30: Overhead | D30: G&A | E30: Total Cost Input | F30: FFP Total Price | G30: vs. Base Case
A31: Base Case | B31: =Indirect_Rates!B6 | C31: =Indirect_Rates!B7 | D31: =Indirect_Rates!B8 | E31: =D12*(1+B31+C31)*(1+D31) | F31: =E31*(1+Indirect_Rates!B14) | G31: ="-"
A32: Low Rates | B32: =Indirect_Rates!C6 | C32: =Indirect_Rates!C7 | D32: =Indirect_Rates!C8 | E32: =D12*(1+B32+C32)*(1+D32) | F32: =E32*(1+Indirect_Rates!C14) | G32: =(F32-F31)/F31
A33: High Rates | B33: =Indirect_Rates!D6 | C33: =Indirect_Rates!D7 | D33: =Indirect_Rates!D8 | E33: =D12*(1+B33+C33)*(1+D33) | F33: =E33*(1+Indirect_Rates!D14) | G33: =(F33-F31)/F31
A35: Analyst Note: The swing between Low and High rate scenarios represents the financial risk a program manager must account for when DCAA adjusts provisional rates mid-contract.

Sheet Profitability
A1: Program Profitability Tracker
A2: Contract ceiling and award data: USASpending.gov | Monthly actuals: Modeled synthetic projections
A4: CONTRACT PROFITABILITY SUMMARY | Based on YTD actuals
A5: Contract | B5: Award ID (USASpending) | C5: Type | D5: Ceiling | E5: Costs Incurred | F5: Revenue Recognized | G5: Gross Margin $ | H5: Margin % | I5: Fee at Risk
A6: CMS Marketplace State Security & Privacy Support | B6: 75FCMC22F0046 | C6: CPFF | D6: 8070000 | E6: 4938996 | F6: =E6*(1+Indirect_Rates!B12) | G6: =F6-E6 | H6: =G6/F6 | I6: =MAX(0,(E6/D6-0.9)*D6*Indirect_Rates!B12)
A7: DHS Program Management & Consulting Support | B7: 70T02021F7560N005 | C7: T&M | D7: 1010000 | E7: 874650 | F7: =E7*(1+Indirect_Rates!B13) | G7: =F7-E7 | H7: =G7/F7 | I7: =MAX(0,(E7/D7-0.9)*D7*Indirect_Rates!B13)
A8: NIH Hosting & Storage IT Support Services | B8: 75N97023F00001 | C8: FFP | D8: 7340000 | E8: 5793540 | F8: =E8*(1+Indirect_Rates!B14) | G8: =F8-E8 | H8: =G8/F8 | I8: =MAX(0,(E8/D8-0.9)*D8*Indirect_Rates!B14)
A9: PORTFOLIO TOTAL | D9: =SUM(D6:D8) | E9: =SUM(E6:E8) | F9: =SUM(F6:F8) | G9: =SUM(G6:G8) | H9: =G9/F9 | I9: =SUM(I6:I8)
A11: MONTHLY PROFITABILITY TREND | Synthetic actuals calibrated to real USASpending.gov award values
A12: Month | B12: Contract | C12: Type | D12: Cost Incurred | E12: Revenue | F12: Gross Margin | G12: Margin %
A13: 2024-01 | B13: CMS Marketplace | C13: CPFF | D13: 250831.7 | E13: 268389.92 | F13: =F13-E13 | G13: =G13/F13
A14: 2024-02 | B14: CMS Marketplace | C14: CPFF | D14: 304484.49 | E14: 325798.4 | F14: =F14-E14 | G14: =G14/F14
A15: 2024-03 | B15: CMS Marketplace | C15: CPFF | D15: 342842.38 | E15: 366841.35 | F15: =F15-E15 | G15: =G15/F15
A16: 2024-04 | B16: CMS Marketplace | C16: CPFF | D16: 382172.65 | E16: 408924.74 | F16: =F16-E16 | G16: =G16/F16
A17: 2024-05 | B17: CMS Marketplace | C17: CPFF | D17: 370470.43 | E17: 396403.36 | F17: =F17-E17 | G17: =G17/F17
A18: 2024-06 | B18: CMS Marketplace | C18: CPFF | D18: 411633.11 | E18: 440447.43 | F18: =F18-E18 | G18: =G18/F18
A19: 2024-07 | B19: CMS Marketplace | C19: CPFF | D19: 408756.99 | E19: 437369.98 | F19: =F19-E19 | G19: =G19/F19
A20: 2024-08 | B20: CMS Marketplace | C20: CPFF | D20: 475744.01 | E20: 509046.09 | F20: =F20-E20 | G20: =G20/F20
A21: 2024-09 | B21: CMS Marketplace | C21: CPFF | D21: 424708.43 | E21: 454438.02 | F21: =F21-E21 | G21: =G21/F21
A22: 2024-10 | B22: CMS Marketplace | C22: CPFF | D22: 385065.26 | E22: 412019.83 | F22: =F22-E22 | G22: =G22/F22
A23: 2024-11 | B23: CMS Marketplace | C23: CPFF | D23: 244593.28 | E23: 261714.81 | F23: =F23-E23 | G23: =G23/F23
A24: 2024-12 | B24: CMS Marketplace | C24: CPFF | D24: 217770.85 | E24: 233014.81 | F24: =F24-E24 | G24: =G24/F24
... A48: 2024-12 | B48: NIH Hosting | C48: FFP | D48: 144674.97 | E48: 162035.97 | F48: =F48-E48 | G48: =G48/F48
A49: TOTAL | D49: =SUM(D13:D48) | E49: =SUM(E13:E48) | F49: =SUM(F13:F48) | G49: =G49/F49
A51: Analyst Note: Cost incurred (blue) is synthetic data modeled from real USASpending.gov award ceilings. Revenue and margin are formula-driven from cost and fee rates in Indirect_Rates tab.
